wallbox_modbus/__init__.py
wallbox_modbus/constants.py
wallbox_modbus/wallbox_modbus.py
wallbox_modbus-0.0.1.dist-info/LICENSE
wallbox_modbus-0.0.1.dist-info/METADATA
wallbox_modbus-0.0.1.dist-info/WHEEL
wallbox_modbus-0.0.1.dist-info/top_level.txt
wallbox_modbus-0.0.1.dist-info/RECORD
